mkdocs_to_confluence/__init__.py
mkdocs_to_confluence/exporter.py
mkdocs_to_confluence/plugin.py
mkdocs_to_confluence/_vendor/LICENSE-md2cf.txt
mkdocs_to_confluence/_vendor/__init__.py
mkdocs_to_confluence/_vendor/md2cf/__init__.py
mkdocs_to_confluence/_vendor/md2cf/__main__.py
mkdocs_to_confluence/_vendor/md2cf/api.py
mkdocs_to_confluence/_vendor/md2cf/confluence_renderer.py
mkdocs_to_confluence/_vendor/md2cf/console_output.py
mkdocs_to_confluence/_vendor/md2cf/document.py
mkdocs_to_confluence/_vendor/md2cf/ignored_files.py
mkdocs_to_confluence/_vendor/md2cf/tui.py
mkdocs_to_confluence/_vendor/md2cf/upsert.py
mkdocs_to_confluence-0.6.0.dist-info/METADATA
mkdocs_to_confluence-0.6.0.dist-info/WHEEL
mkdocs_to_confluence-0.6.0.dist-info/entry_points.txt
mkdocs_to_confluence-0.6.0.dist-info/licenses/LICENSE
mkdocs_to_confluence-0.6.0.dist-info/RECORD
