Metadata-Version: 2.4
Name: mkdocs-to-confluence
Version: 0.6.0
Summary: MkDocs plugin for converting and uploading Markdown pages to Confluence with automatic synchronization (via REST API)
Project-URL: Homepage, https://github.com/jmanteau/mkdocs-to-confluence
Project-URL: Repository, https://github.com/jmanteau/mkdocs-to-confluence
Project-URL: Bug Tracker, https://github.com/jmanteau/mkdocs-to-confluence/issues
Author-email: Julien Manteau <jmanteau@gmail.com>
License: MIT
License-File: LICENSE
Keywords: confluence,documentation,markdown,mkdocs,python,rest,sync,synchronization
Classifier: Development Status :: 4 - Beta
Classifier: Intended Audience :: Developers
Classifier: License :: OSI Approved :: MIT License
Classifier: Operating System :: OS Independent
Classifier: Programming Language :: Python :: 3
Classifier: Programming Language :: Python :: 3.8
Classifier: Programming Language :: Python :: 3.9
Classifier: Programming Language :: Python :: 3.10
Classifier: Programming Language :: Python :: 3.11
Classifier: Programming Language :: Python :: 3.12
Classifier: Topic :: Documentation
Classifier: Topic :: Software Development :: Documentation
Requires-Python: >=3.8
Requires-Dist: jinja2
Requires-Dist: mime>=0.1.0
Requires-Dist: mistune>=3.1.2
Requires-Dist: mkdocs>=1.1
Requires-Dist: requests
